mucus/__init__.py
mucus/cli.py
mucus/command.py
mucus/config.py
mucus/config_default.yaml
mucus/exception.py
mucus/history.py
mucus/lazy.py
mucus/song.py
mucus/commands/__init__.py
mucus/commands/assist.py
mucus/commands/clear.py
mucus/commands/download.py
mucus/commands/exit.py
mucus/commands/help.py
mucus/commands/loop.py
mucus/commands/next.py
mucus/commands/pause.py
mucus/commands/queue.py
mucus/commands/search.py
mucus/commands/song.py
mucus/commands/start.py
mucus/commands/stop.py
mucus/deezer/auth.py
mucus/deezer/client.py
mucus/deezer/decrypter.py
mucus/deezer/exception.py
mucus/deezer/page.py
mucus/deezer/stream.py
mucus/play/history.py
mucus/play/player.py
mucus-0.1.3.dist-info/entry_points.txt
mucus-0.1.3.dist-info/LICENSE
mucus-0.1.3.dist-info/WHEEL
mucus-0.1.3.dist-info/METADATA
mucus-0.1.3.dist-info/RECORD
