Metadata-Version: 2.1
Name: mucus
Version: 0.1.3
Summary: mucus
Author-email: Chris Coleman <chris@chriscoleman.uk>
Classifier: License :: OSI Approved :: MIT License
Requires-Dist: appdirs
Requires-Dist: click
Requires-Dist: confuse
Requires-Dist: redis
Requires-Dist: rich
Requires-Dist: myass
Requires-Dist: pycryptodome
Requires-Dist: yaspin
